square/__init__.py
square/__main__.py
siril_square-1.0.dist-info/LICENSE
siril_square-1.0.dist-info/METADATA
siril_square-1.0.dist-info/WHEEL
siril_square-1.0.dist-info/entry_points.txt
siril_square-1.0.dist-info/top_level.txt
siril_square-1.0.dist-info/RECORD
